{"L":[
{
"LN":"Layer 1",
"FR":[
{
"I":0,
"DU":33,
"E":[
{"ASI":{
"MX":[1,0,0,1,0,0],
"N":"349"
}}]},{
"I":33,
"DU":2,
"E":[
{"ASI":{
"MX":[1,0,0,1,0,4.75],
"N":"350"
}}]},{
"I":35,
"DU":1,
"E":[
{"ASI":{
"MX":[1,0,0,1,-2.9,21.55],
"N":"351"
}}]},{
"I":36,
"DU":1,
"E":[
{"ASI":{
"MX":[1,0,0,1,-0.1,20.3],
"N":"352"
}}]},{
"I":37,
"DU":1,
"E":[
{"ASI":{
"MX":[1,0,0,1,0,16.6],
"N":"353"
}}]},{
"I":38,
"DU":2,
"E":[
{"ASI":{
"MX":[1,0,0,1,0,-4],
"N":"354"
}}]},{
"I":40,
"DU":6,
"E":[
{"ASI":{
"MX":[1,0,0,1,0,0],
"N":"355"
}}]}
]}
]}